slipstream_api-3.52-py2.7-nspkg.pth
slipstream/api/__init__.py
slipstream/api/api.py
slipstream/api/models.py
slipstream_api-3.52.dist-info/DESCRIPTION.rst
slipstream_api-3.52.dist-info/METADATA
slipstream_api-3.52.dist-info/RECORD
slipstream_api-3.52.dist-info/WHEEL
slipstream_api-3.52.dist-info/metadata.json
slipstream_api-3.52.dist-info/namespace_packages.txt
slipstream_api-3.52.dist-info/top_level.txt
