Metadata-Version: 2.0
Name: slipstream-api
Version: 3.52
Summary: A wrapper to use SlipStream from Python programs.
Home-page: http://sixsq.com/slipstream
Author: SixSq Sarl
Author-email: support@sixsq.com
License: Apache License, Version 2.0
Keywords: slipstream devops api
Platform: UNKNOWN
Classifier: Development Status :: 4 - Beta
Classifier: License :: OSI Approved :: Apache Software License
Classifier: Intended Audience :: Developers
Classifier: Intended Audience :: System Administrators
Classifier: Operating System :: OS Independent
Classifier: Programming Language :: Python
Classifier: Programming Language :: Python :: 2
Classifier: Programming Language :: Python :: 2.6
Classifier: Programming Language :: Python :: 2.7
Classifier: Programming Language :: Python :: 3
Classifier: Programming Language :: Python :: 3.3
Classifier: Programming Language :: Python :: 3.4
Classifier: Programming Language :: Python :: 3.5
Classifier: Programming Language :: Python :: 3.6
Classifier: Topic :: Software Development
Requires-Dist: requests
Requires-Dist: six
Requires-Dist: configparser
